my_own_package/__init__.py
Mihai_first_package-0.2.0.dist-info/METADATA
Mihai_first_package-0.2.0.dist-info/WHEEL
Mihai_first_package-0.2.0.dist-info/top_level.txt
Mihai_first_package-0.2.0.dist-info/RECORD
