Metadata-Version: 2.1
Name: Mihai-first-package
Version: 0.2.0
Summary: This is my first time when i made my own package
Home-page: UNKNOWN
Author: Avram Mihai
Author-email: railgundrop@gmail.com
License: UNKNOWN
Platform: UNKNOWN
